[
  {
    "id": "tabs",
    "label": "列表配置信息",
    "value": "[]",
    "type": "CodeData"
  },
  {
    "id": "px",
    "label": "标题左右间距",
    "value": 40,
    "type": "Number"
  },
  {
    "id": "nameKey",
    "label": "取name的字段",
    "value": "name",
    "type": "Text"
  },
  {
    "id": "value",
    "label": "当前显示的下标 (使用v-model语法糖: 1.props需为value; 2.需回调input事件)",
    "value": 0,
    "type": "Text"
  },
  {
    "id": "fixed",
    "label": "是否悬浮,默认false",
    "value": false,
    "type": "Switch"
  },
  {
    "id": "tabWidth",
    "label": "每个tab的宽度",
    "value": 0,
    "type": "Number"
  },
  {
    "id": "tabRight",
    "label": "tab的偏移量,默认为0,为flex平均分配; 如果指定偏移量,则不使用flex,每个tab居左,超过则水平滑动(单位默认rpx)",
    "value": 0,
    "type": "Number"
  },
  {
    "id": "height",
    "label": "高度,单位rpx",
    "value": 80,
    "type": "Number"
  },
  {
    "id": "bcColor",
    "label": "列表栏背景颜色",
    "value": "transparent",
    "type": "Text"
  },
  {
    "id": "cColor",
    "label": "列表栏字体颜色",
    "value": "#000",
    "type": "Text"
  },
  {
    "id": "blColor",
    "label": "列表栏下划线颜色",
    "value": "#479ff7",
    "type": "Text"
  }
]
